marge_pytorch/__init__.py
marge_pytorch/autoregressive_wrapper.py
marge_pytorch/marge_pytorch.py
marge_pytorch-0.2.9.dist-info/LICENSE
marge_pytorch-0.2.9.dist-info/METADATA
marge_pytorch-0.2.9.dist-info/WHEEL
marge_pytorch-0.2.9.dist-info/top_level.txt
marge_pytorch-0.2.9.dist-info/RECORD
