Metadata-Version: 2.1
Name: marge-pytorch
Version: 0.2.9
Summary: Marge - Pytorch
Home-page: https://github.com/lucidrains/marge-pytorch
Author: Phil Wang
Author-email: lucidrains@gmail.com
License: MIT
Keywords: artificial intelligence,attention mechanism,transformers,pre-training
Platform: UNKNOWN
Classifier: Development Status :: 4 - Beta
Classifier: Intended Audience :: Developers
Classifier: Topic :: Scientific/Engineering :: Artificial Intelligence
Classifier: License :: OSI Approved :: MIT License
Classifier: Programming Language :: Python :: 3.6
Requires-Dist: einops (>=0.3)
Requires-Dist: faiss-gpu
Requires-Dist: numpy
Requires-Dist: torch (>=1.6)
Requires-Dist: tqdm
